quiltplus/__init__.py
quiltplus/api.py
quiltplus/ignore.py
quiltplus/local.py
quiltplus/package.py
quiltplus/path.py
quiltplus/property.py
quiltplus/py.typed
quiltplus/registry.py
quiltplus/resource.py
quiltplus/root.py
quiltplus/type.py
quiltplus/uri.py
quiltplus/versions.py
quiltplus-0.9.7.dist-info/LICENSE.md
quiltplus-0.9.7.dist-info/METADATA
quiltplus-0.9.7.dist-info/WHEEL
quiltplus-0.9.7.dist-info/RECORD
