Metadata-Version: 2.1
Name: quiltplus
Version: 0.9.7
Summary: Async Python API for Quilt's fractal social knowledge platform
License: MIT
Keywords: yaml,api,resource,quilt
Author: Ernest Prabhakar
Author-email: ernest@quiltdata.io
Requires-Python: >=3.10,<4.0
Classifier: License :: OSI Approved :: MIT License
Classifier: Programming Language :: Python :: 3
Classifier: Programming Language :: Python :: 3.10
Classifier: Programming Language :: Python :: 3.11
Requires-Dist: anyio (>=3.7.1,<4.0.0)
Requires-Dist: asyncclick (>=8.1.3.4,<9.0.0.0)
Requires-Dist: fastapi (>=0.104.0,<0.105.0)
Requires-Dist: isort (>=5.12.0,<6.0.0)
Requires-Dist: quilt3 (>=5.1.0,<6.0.0)
Requires-Dist: quiltcore (>=0.3.5,<0.4.0)
Requires-Dist: trio (>=0.22.2,<0.23.0)
Requires-Dist: typing-extensions (>=4.7.1,<5.0.0)
Requires-Dist: tzlocal (>=5.0.1,<6.0.0)
Requires-Dist: un-yaml (>=0.3.1)
Requires-Dist: universal-pathlib (>=0.1.1,<0.2.0)
Requires-Dist: urllib3 (<2)
